AUTHORS
COPYING
ChangeLog
MANIFEST.in
README
setup.py
doc/examples/filelist.py
doc/examples/form-window.py
doc/examples/formapp.glade
doc/examples/iconview.py
doc/examples/iconviewapp.glade
doc/examples/indicator.py
doc/examples/listapp.glade
doc/examples/listbroken.py
doc/examples/listview.py
doc/examples/log_indicator.py
doc/examples/pixmap-extras.py
doc/examples/pixmapapp.glade
doc/examples/pixmaps.py
doc/examples/simple-app.py
doc/examples/simpleapp.glade
doc/examples/threaded-window.py
doc/examples/treecombo.glade
doc/examples/treecombo.glade~
doc/examples/treecombo.py
doc/examples/widget-extras.py
doc/examples/widgetextra.glade
doc/examples/images/complex/image.png
doc/examples/images/complex/other.svg
doc/examples/images/complex/overlay.svg
doc/examples/images/simple/raster.png
doc/examples/images/simple/vector.svg
gtkme/__init__.py
gtkme/asyncme.py
gtkme/forms.py
gtkme/indicator.py
gtkme/listfiles.py
gtkme/listview.py
gtkme/main.py
gtkme/pixmap.py
gtkme/version.py
gtkme/window.py
gtkme.egg-info/PKG-INFO
gtkme.egg-info/SOURCES.txt
gtkme.egg-info/dependency_links.txt
gtkme.egg-info/requires.txt
gtkme.egg-info/top_level.txt