Metadata-Version: 1.0
Name: gtkme
Version: 1.5.1
Summary: Amazing interface for wrapping python-gtk applications and make programming fun again.
Home-page: https://code.launchpad.net/~doctormo
Author: Martin Owens
Author-email: doctormo@gmail.com
License: GPLv3
Platform: linux
